pubsub.py
setup.py
pubsub.egg-info/PKG-INFO
pubsub.egg-info/SOURCES.txt
pubsub.egg-info/dependency_links.txt
pubsub.egg-info/requires.txt
pubsub.egg-info/top_level.txt