Metadata-Version: 1.0
Name: pubsub
Version: 0.1.2
Summary: Simple Python PubSub
Home-page: https://github.com/nehz/pubsub
Author: Zhen Wang
Author-email: mail@zhenwang.info
License: UNKNOWN
Platform: UNKNOWN
